{"bg": {"H": 9, "W": 9, "EndX": 6, "EndY": 2, "BG": [["X", "X", "X", "X", "X", "X", "X", "X", "X"], ["X", ".", ".", ".", "X", ".", ".", ".", "X"], ["X", ".", ".", ".", ".", ".", ".", ".", "X"], ["X", ".", ".", ".", "X", ".", ".", ".", "X"], ["X", "X", ".", "X", "X", "X", "X", "X", "X"], ["X", ".", ".", ".", ".", ".", ".", ".", "X"], ["X", ".", ".", ".", ".", ".", ".", ".", "X"], ["X", ".", ".", ".", ".", ".", ".", ".", "X"], ["X", "X", "X", "X", "X", "X", "X", "X", "X"]]}, "entities": {"player": {"X": 2, "Y": 6, "dir": "U", "alive": true}, "bullet": {"X": 0, "Y": 0, "dir": "U", "alive": false}, "nbBoxes": 2, "Boxes": [{"X": 5, "Y": 5}, {"X": 5, "Y": 7}]}, "logic": {"nb_activators": 3, "activators": [{"X": 7, "Y": 5, "type": "I"}, {"X": 7, "Y": 7, "type": "I"}, {"X": 2, "Y": 2, "type": "I"}], "nb_gates": 1, "gates": [{"X": 4, "Y": 6, "type": "OR", "dir": "U"}], "nb_doors": 2, "doors": [{"X": 4, "Y": 2, "nb_tiles": 1, "tiles": [{"X": 4, "Y": 2}]}, {"X": 2, "Y": 4, "nb_tiles": 1, "tiles": [{"X": 2, "Y": 4}]}], "nb_links": 4, "links": [{"type_start": "Activator", "type_end": "Gate", "nb_nodes": 3, "nodes": [{"X": 7, "Y": 7}, {"X": 4, "Y": 7}, {"X": 4, "Y": 6}], "offsets": [0, -1]}, {"type_start": "Activator", "type_end": "Gate", "nb_nodes": 5, "nodes": [{"X": 7, "Y": 5}, {"X": 5, "Y": 5}, {"X": 5, "Y": 7}, {"X": 4, "Y": 7}, {"X": 4, "Y": 6}], "offsets": [0, 0, -3, 2]}, {"type_start": "Gate", "type_end": "Door", "nb_nodes": 4, "nodes": [{"X": 4, "Y": 6}, {"X": 4, "Y": 5}, {"X": 2, "Y": 5}, {"X": 2, "Y": 4}], "offsets": [0, 0, 0]}, {"type_start": "Activator", "type_end": "Door", "nb_nodes": 2, "nodes": [{"X": 2, "Y": 2}, {"X": 4, "Y": 2}], "offsets": [0]}]}, "text": ["This is an OR logic gate,", "at least one of its inputs need to be activated for it to activate."], "flags": {"can_swap": false}}